selenium_web_automation_utils/__init__.py
selenium_web_automation_utils/compatibility.py
selenium_web_automation_utils/logging_listener.py
selenium_web_automation_utils/logging_utils.py
selenium_web_automation_utils/selenium_utils.py
selenium_web_automation_utils-0.3.12.dist-info/licenses/LICENSE
selenium_web_automation_utils-0.3.12.dist-info/METADATA
selenium_web_automation_utils-0.3.12.dist-info/WHEEL
selenium_web_automation_utils-0.3.12.dist-info/top_level.txt
selenium_web_automation_utils-0.3.12.dist-info/RECORD
