Metadata-Version: 2.4
Name: selenium-web-automation-utils
Version: 0.3.12
Summary: A lightweight Selenium automation utility package.
Home-page: https://github.com/roamingsaint/selenium-web-automation-utils
Author: Kanad Rishiraj (@RoamingSaint)
Author-email: "Kanad Rishiraj (RoamingSaint)" <roamingsaint27@gmail.com>
License: MIT License
Project-URL: Homepage, https://github.com/roamingsaint/selenium-web-automation-utils
Project-URL: Repository, https://github.com/roamingsaint/selenium-web-automation-utils
Project-URL: Bug Tracker, https://github.com/roamingsaint/selenium-web-automation-utils/issues
Requires-Python: >=3.7
License-File: LICENSE
Requires-Dist: selenium
Requires-Dist: setuptools
Requires-Dist: undetected-chromedriver
Requires-Dist: colorlog
Dynamic: author
Dynamic: home-page
Dynamic: license-file
Dynamic: requires-python
